pcffont/__init__.py
pcffont/builder.py
pcffont/error.py
pcffont/font.py
pcffont/format.py
pcffont/glyph.py
pcffont/header.py
pcffont/metric.py
pcffont/table.py
pcffont/tables/__init__.py
pcffont/tables/accelerators.py
pcffont/tables/bitmaps.py
pcffont/tables/encodings.py
pcffont/tables/factory.py
pcffont/tables/glyph_names.py
pcffont/tables/metrics.py
pcffont/tables/properties.py
pcffont/tables/scalable_widths.py
pcffont/utils/__init__.py
pcffont/utils/stream.py
pcffont-0.0.24.dist-info/WHEEL
pcffont-0.0.24.dist-info/METADATA
pcffont-0.0.24.dist-info/RECORD
