Metadata-Version: 2.4
Name: pcffont
Version: 0.0.24
Summary: A library for manipulating Portable Compiled Format (PCF) Fonts
Keywords: pcf,font
Author: TakWolf
License-Expression: MIT
Classifier: Programming Language :: Python :: 3
Classifier: Programming Language :: Python :: 3.10
Classifier: Programming Language :: Python :: 3.11
Classifier: Programming Language :: Python :: 3.12
Classifier: Programming Language :: Python :: 3.13
Classifier: Programming Language :: Python :: 3.14
Classifier: License :: OSI Approved :: MIT License
Classifier: Operating System :: OS Independent
Maintainer: TakWolf
Requires-Python: >=3.10
Project-URL: Homepage, https://github.com/TakWolf/pcffont-python
Project-URL: Issues, https://github.com/TakWolf/pcffont-python/issues
Project-URL: Source, https://github.com/TakWolf/pcffont-python
